flipflop-jk-advanced/flipflop-jk-advanced.v
module JK_FF_Advanced (
    input wire J,         // Entrada J
    input wire K,         // Entrada K
    input wire clk,       // Reloj
    input wire reset_async,  // Reset asincrónico
    input wire enable,    // Señal de habilitación
    output reg Q,        // Salida Q
    output wire Q_bar     // Salida Q_bar
);
// Asignamos el valor de Q_bar como el complemento de Q
    assign Q_bar = ~Q;

    always @(posedge clk or posedge reset_async) begin
        if (reset_async) begin
            Q <= 1'b0;   // Reset asincrónico, establece Q a 0
        end else if (enable) begin
            case ({J, K})
                2'b00: Q <= Q;   // No change
                2'b01: Q <= 1'b0;  // Reset
                2'b10: Q <= 1'b1;  // Set
                2'b11:Q <= ~Q;  // Toggle
                default: Q <= Q;  // Default case (redundante)
            endcase
        end
    end
endmodule


/* OTRO CASO EXPLICITANDO MAS Q_BAR:

   always @(posedge clk or posedge reset_async) begin
        if (reset_async) begin
            Q <= 1'b0;   // Reset asincrónico, establece Q a 0
            Q_bar <= 1'b1; // Reset asincrónico, establece Q_bar a 1
        end else if (enable) begin
            case ({J, K})
                2'b00: begin  // No change
                    Q <= Q;
                    Q_bar <= Q_bar;
                end
                2'b01: begin  // Reset
                    Q <= 1'b0;
                    Q_bar <= 1'b1;
                end
                2'b10: begin  // Set
                    Q <= 1'b1;
                    Q_bar <= 1'b0;
                end
                2'b11: begin  // Toggle
                    Q <= ~Q;
                    Q_bar <= ~Q_bar;
                end
            endcase
        end
    end

*/

flipflop-jk-advanced/flipflop-jk-advanced_tb.v
`timescale 1ns / 1ps
`default_nettype none
`define DUMPSTR(x) `"x.vcd`"

module JK_FF_Advanced_tb;

    // Parámetros de tiempo
    parameter PERIOD = 10; // Periodo del reloj (en unidades de tiempo)
    
    // Declaración de señales
    reg J;               // Entrada J
    reg K;               // Entrada K
    reg clk;             // Reloj
    reg reset_async;     // Reset asincrónico
    reg enable;          // Señal de habilitación
    wire Q;              // Salida Q
    wire Q_bar;          // Salida Q_bar

    // Instancia del flip-flop JK avanzado
    JK_FF_Advanced uut (
        .J(J),
        .K(K),
        .clk(clk),
        .reset_async(reset_async),
        .enable(enable),
        .Q(Q),
        .Q_bar(Q_bar)
    );

    // Generación del reloj
    always #((PERIOD / 2)) clk = ~clk; // Genera un ciclo de reloj de 50% de duty cycle

    // Inicialización de señales
    initial begin
        $dumpfile(`DUMPSTR(`VCD_OUTPUT));
        $dumpvars(0, JK_FF_Advanced_tb);

        clk = 0;
        reset_async = 1; // Activa el reset asincrónico inicialmente
        enable = 0;      // Desactiva la señal de habilitación inicialmente
        #100;            // Espera un poco de tiempo
        reset_async = 0; // Desactiva el reset asincrónico
        #100;            // Espera un poco de tiempo

        // Prueba de diferentes valores de entrada J y K con habilitación desactivada
        #10 J = 0; K = 0; #10 J = 0; K = 1; #10 J = 1; K = 0; #10 J = 1; K = 1;
        #100; // Espera un poco de tiempo

        // Habilita la señal de habilitación
        enable = 1;
        #100; // Espera un poco de tiempo

        // Prueba de diferentes valores de entrada J y K con habilitación activada
        #10 J = 0; K = 0; #10 J = 0; K = 1; #10 J = 1; K = 0; #10 J = 1; K = 1;
        #100; // Espera un poco de tiempo

        // Finaliza la simulación
        $finish;
    end

    // Monitorear cambios en las señales
    initial begin
        $monitor("Time=%0t, J=%b, K=%b, clk=%b, reset_async=%b, enable=%b, Q=%b, Q_bar=%b", $time, J, K, clk, reset_async, enable, Q, Q_bar);
    end

endmodule

/*
    Un ciclo de reloj de 50% de duty cycle se refiere a un ciclo de reloj donde la señal 
    de reloj pasa la mitad del tiempo en estado alto y la otra mitad del tiempo en estado 
    bajo durante cada período del reloj. Esto significa que el tiempo que la señal de reloj 
    permanece en estado alto es igual al tiempo que permanece en estado bajo.


        ____       ____       ____       ____       ____       ____       ____   
        |    |     |    |     |    |     |    |     |    |     |    |     |    |  
    ____|    |_____|    |_____|    |_____|    |_____|    |_____|    |_____|    |_
        ↑             ↑             ↑             ↑             ↑             ↑   
    Tiempo         Tiempo        Tiempo        Tiempo        Tiempo        Tiempo 
    Transcurrido   Transcurrido  Transcurrido  Transcurrido  Transcurrido  Transcurrido
    (Alto)         (Bajo)        (Alto)        (Bajo)        (Alto)        (Bajo)

*/

flipflop-jk-advanced/flipflop-jk-advanced_tb.vcd
$date
	Wed May 15 15:03:12 2024
$end
$version
	Icarus Verilog
$end
$timescale
	1ps
$end
$scope module JK_FF_Advanced_tb $end
$var wire 1 ! Q_bar $end
$var wire 1 " Q $end
$var parameter 32 # PERIOD $end
$var reg 1 $ J $end
$var reg 1 % K $end
$var reg 1 & clk $end
$var reg 1 ' enable $end
$var reg 1 ( reset_async $end
$scope module uut $end
$var wire 1 $ J $end
$var wire 1 % K $end
$var wire 1 ! Q_bar $end
$var wire 1 & clk $end
$var wire 1 ' enable $end
$var wire 1 ( reset_async $end
$var reg 1 " Q $end
$upscope $end
$upscope $end
$enddefinitions $end
$comment Show the parameter values. $end
$dumpall
b1010 #
$end
#0
$dumpvars
1(
0'
0&
x%
x$
0"
1!
$end
#5000
1&
#10000
0&
#15000
1&
#20000
0&
#25000
1&
#30000
0&
#35000
1&
#40000
0&
#45000
1&
#50000
0&
#55000
1&
#60000
0&
#65000
1&
#70000
0&
#75000
1&
#80000
0&
#85000
1&
#90000
0&
#95000
1&
#100000
0&
0(
#105000
1&
#110000
0&
#115000
1&
#120000
0&
#125000
1&
#130000
0&
#135000
1&
#140000
0&
#145000
1&
#150000
0&
#155000
1&
#160000
0&
#165000
1&
#170000
0&
#175000
1&
#180000
0&
#185000
1&
#190000
0&
#195000
1&
#200000
0&
#205000
1&
#210000
0&
0%
0$
#215000
1&
#220000
0&
1%
#225000
1&
#230000
0&
0%
1$
#235000
1&
#240000
0&
1%
#245000
1&
#250000
0&
#255000
1&
#260000
0&
#265000
1&
#270000
0&
#275000
1&
#280000
0&
#285000
1&
#290000
0&
#295000
1&
#300000
0&
#305000
1&
#310000
0&
#315000
1&
#320000
0&
#325000
1&
#330000
0&
#335000
1&
#340000
0&
1'
#345000
0!
1"
1&
#350000
0&
#355000
1!
0"
1&
#360000
0&
#365000
0!
1"
1&
#370000
0&
#375000
1!
0"
1&
#380000
0&
#385000
0!
1"
1&
#390000
0&
#395000
1!
0"
1&
#400000
0&
#405000
0!
1"
1&
#410000
0&
#415000
1!
0"
1&
#420000
0&
#425000
0!
1"
1&
#430000
0&
#435000
1!
0"
1&
#440000
0&
#445000
0!
1"
1&
#450000
0&
0%
0$
#455000
1&
#460000
0&
1%
#465000
1!
0"
1&
#470000
0&
0%
1$
#475000
0!
1"
1&
#480000
0&
1%
#485000
1!
0"
1&
#490000
0&
#495000
0!
1"
1&
#500000
0&
#505000
1!
0"
1&
#510000
0&
#515000
0!
1"
1&
#520000
0&
#525000
1!
0"
1&
#530000
0&
#535000
0!
1"
1&
#540000
0&
#545000
1!
0"
1&
#550000
0&
#555000
0!
1"
1&
#560000
0&
#565000
1!
0"
1&
#570000
0&
#575000
0!
1"
1&
