flipflop-d-advanced/flipflop-d-advanced.v
module D_FF_Advanced (
    input wire D,         // Entrada de datos
    input wire clk,       // Reloj
    input wire reset_async,  // Reset asincrónico
    input wire reset_sync,   // Reset síncrono
    input wire enable,    // Señal de habilitación
    output reg Q         // Salida Q
);

    always @(posedge clk or posedge reset_async or posedge reset_sync) begin
        if (reset_async) begin
            Q <= 1'b0;  // Reset asincrónico, establece Q a 0
        end else if (reset_sync) begin
            Q <= 1'b0;  // Reset síncrono, establece Q a 0 en el flanco de subida del reloj
        end else if (enable) begin
            Q <= D;     // Almacena el valor de D en el flanco de subida del reloj si la señal de habilitación está activa
        end
    end

endmodule

flipflop-d-advanced/flipflop-d-advanced_tb.v
`timescale 1ns / 1ps
`default_nettype none
`define DUMPSTR(x) `"x.vcd`"

module D_FF_Advanced_tb;

    // Parámetros de tiempo
    parameter PERIOD = 10; // Periodo del reloj (en unidades de tiempo)
    
    // Declaración de señales
    reg D;               // Entrada de datos
    reg clk;             // Reloj
    reg reset_async;     // Reset asincrónico
    reg reset_sync;      // Reset síncrono
    reg enable;          // Señal de habilitación
    wire Q;              // Salida Q

    // Instancia del flip-flop D avanzado
    D_FF_Advanced uut (
        .D(D),
        .clk(clk),
        .reset_async(reset_async),
        .reset_sync(reset_sync),
        .enable(enable),
        .Q(Q)
    );

    // Generación del reloj
    always #((PERIOD / 2)) clk = ~clk; // Genera un ciclo de reloj de 50% de duty cycle

    // Inicialización de señales
    initial begin
        $dumpfile(`DUMPSTR(`VCD_OUTPUT));
        $dumpvars(0, D_FF_Advanced_tb);

        clk = 0;
        reset_async = 1; // Activa el reset asincrónico inicialmente
        reset_sync = 1;  // Activa el reset síncrono inicialmente
        enable = 0;      // Desactiva la señal de habilitación inicialmente
        #100;            // Espera un poco de tiempo
        reset_async = 0; // Desactiva el reset asincrónico
        reset_sync = 0;  // Desactiva el reset síncrono
        #100;            // Espera un poco de tiempo

        // Prueba de diferentes valores de entrada D con habilitación desactivada
        #10 D = 1; #10 D = 0; #10 D = 1; #10 D = 0; #10 D = 1; #10 D = 0; #10 D = 1; #10 D = 0;
        #100; // Espera un poco de tiempo

        // Habilita la señal de habilitación
        enable = 1;
        #100; // Espera un poco de tiempo

        // Prueba de diferentes valores de entrada D con habilitación activada
        #10 D = 1; #10 D = 0; #10 D = 1; #10 D = 0; #10 D = 1; #10 D = 0; #10 D = 1; #10 D = 0;
        #100; // Espera un poco de tiempo

        // Activa el reset síncrono
        reset_sync = 1;
        #10 reset_sync = 0;
        #100; // Espera un poco de tiempo

        // Activa el reset asincrónico
        reset_async = 1;
        #10 reset_async = 0;
        #100; // Espera un poco de tiempo

        // Finaliza la simulación
        $finish;
    end

    // Monitorear cambios en las señales
    initial begin
        $monitor("Time=%0t, D=%b, clk=%b, reset_async=%b, reset_sync=%b, enable=%b, Q=%b", $time, D, clk, reset_async, reset_sync, enable, Q);
    end

endmodule

flipflop-d-advanced/flipflop-d-advanced_tb.vcd
$date
	Wed May 15 14:17:05 2024
$end
$version
	Icarus Verilog
$end
$timescale
	1ps
$end
$scope module D_FF_Advanced_tb $end
$var wire 1 ! Q $end
$var parameter 32 " PERIOD $end
$var reg 1 # D $end
$var reg 1 $ clk $end
$var reg 1 % enable $end
$var reg 1 & reset_async $end
$var reg 1 ' reset_sync $end
$scope module uut $end
$var wire 1 # D $end
$var wire 1 $ clk $end
$var wire 1 % enable $end
$var wire 1 & reset_async $end
$var wire 1 ' reset_sync $end
$var reg 1 ! Q $end
$upscope $end
$upscope $end
$enddefinitions $end
$comment Show the parameter values. $end
$dumpall
b1010 "
$end
#0
$dumpvars
1'
1&
0%
0$
x#
0!
$end
#5000
1$
#10000
0$
#15000
1$
#20000
0$
#25000
1$
#30000
0$
#35000
1$
#40000
0$
#45000
1$
#50000
0$
#55000
1$
#60000
0$
#65000
1$
#70000
0$
#75000
1$
#80000
0$
#85000
1$
#90000
0$
#95000
1$
#100000
0$
0'
0&
#105000
1$
#110000
0$
#115000
1$
#120000
0$
#125000
1$
#130000
0$
#135000
1$
#140000
0$
#145000
1$
#150000
0$
#155000
1$
#160000
0$
#165000
1$
#170000
0$
#175000
1$
#180000
0$
#185000
1$
#190000
0$
#195000
1$
#200000
0$
#205000
1$
#210000
0$
1#
#215000
1$
#220000
0$
0#
#225000
1$
#230000
0$
1#
#235000
1$
#240000
0$
0#
#245000
1$
#250000
0$
1#
#255000
1$
#260000
0$
0#
#265000
1$
#270000
0$
1#
#275000
1$
#280000
0$
0#
#285000
1$
#290000
0$
#295000
1$
#300000
0$
#305000
1$
#310000
0$
#315000
1$
#320000
0$
#325000
1$
#330000
0$
#335000
1$
#340000
0$
#345000
1$
#350000
0$
#355000
1$
#360000
0$
#365000
1$
#370000
0$
#375000
1$
#380000
0$
1%
#385000
1$
#390000
0$
#395000
1$
#400000
0$
#405000
1$
#410000
0$
#415000
1$
#420000
0$
#425000
1$
#430000
0$
#435000
1$
#440000
0$
#445000
1$
#450000
0$
#455000
1$
#460000
0$
#465000
1$
#470000
0$
#475000
1$
#480000
0$
#485000
1$
#490000
0$
1#
#495000
1!
1$
#500000
0$
0#
#505000
0!
1$
#510000
0$
1#
#515000
1!
1$
#520000
0$
0#
#525000
0!
1$
#530000
0$
1#
#535000
1!
1$
#540000
0$
0#
#545000
0!
1$
#550000
0$
1#
#555000
1!
1$
#560000
0$
0#
#565000
0!
1$
#570000
0$
#575000
1$
#580000
0$
#585000
1$
#590000
0$
#595000
1$
#600000
0$
#605000
1$
#610000
0$
#615000
1$
#620000
0$
#625000
1$
#630000
0$
#635000
1$
#640000
0$
#645000
1$
#650000
0$
#655000
1$
#660000
0$
1'
#665000
1$
#670000
0$
0'
#675000
1$
#680000
0$
#685000
1$
#690000
0$
#695000
1$
#700000
0$
#705000
1$
#710000
0$
#715000
1$
#720000
0$
#725000
1$
#730000
0$
#735000
1$
#740000
0$
#745000
1$
#750000
0$
#755000
1$
#760000
0$
#765000
1$
#770000
0$
1&
#775000
1$
#780000
0$
0&
