flipflop-jk/flipflop-jk.v
module JK_FF(
    input wire J, //S
    input wire K, //R
    input wire clk,
    input wire reset,
    output reg Q,
    output wire Q_bar
);
// Asignamos el valor de Q_bar como el complemento de Q
    assign Q_bar = ~Q;

//Bloque siempre sensible al flanco positivo del reloj o del reset
    always @(posedge clk or posedge reset) begin
        if (reset) begin
            Q <= 1'b0; //Resetea 
    end else begin
            case({J,K})
                2'b00: Q <= Q;        // No cambia
                2'b01: Q <= 1'b0;     // Resetea Q
                2'b10: Q <= 1'b1;     // Setea Q
                2'b11: Q <= ~Q;       // Toggle
                default: Q <= Q;      // Default case (redundante)
            endcase
        end
    end

endmodule

/*
EXTRA:

<=: Operador de asignación no bloqueante
    En los bloques secuenciales (always sensibles al reloj o reset), 
    se utiliza la asignación no bloqueante para garantizar que todas 
    las asignaciones ocurren simultáneamente al final del ciclo de reloj


*/

flipflop-jk/flip-flop-jk_tb.v
`default_nettype none
`define DUMPSTR(x) `"x.vcd`"
`timescale 1ns / 1ps

module JK_FF_tb;

// Declaración de señales
    reg J;
    reg K;
    reg clk;
    reg reset;
    wire Q;
    wire Q_bar;

// Instancia del módulo JK_FF
    JK_FF uut (
        .J(J),
        .K(K),
        .clk(clk),
        .reset(reset),
        .Q(Q),
        .Q_bar(Q_bar)
    );

// Generación del reloj
    always #5 clk = ~clk;

// Bloque inicial para la simulación
    initial begin
        $dumpfile(`DUMPSTR(`VCD_OUTPUT));
        $dumpvars(0, JK_FF_tb);

    // Inicialización de señales
        clk = 0;
        reset = 0;
        J = 0;
        K = 0;
    
    // Aplicación de reset
        #10 reset = 1;
        #10 reset = 0;

    // Prueba de diferentes combinaciones de J y K
        #10 J = 0; K = 0; // No change
        #10 J = 0; K = 1; // Reset Q
        #10 J = 1; K = 0; // Set Q
        #10 J = 1; K = 1; // Toggle Q
        #10 J = 0; K = 1; // Reset Q
        #10 J = 1; K = 0; // Set Q
        #10 J = 1; K = 1; // Toggle Q

        // Finalizar simulación
        #50 $finish;
    end

endmodule

/*
#10: El simulador esperará otras 10 unidades de tiempo antes de ejecutar

EJ: #10 reset = 1;
El simulador esperará 10 unidades de tiempo antes de ejecutar la instrucción reset = 1;.

*/

flipflop-jk/flip-flop-jk_tb.vcd
$date
	Wed May 15 14:57:48 2024
$end
$version
	Icarus Verilog
$end
$timescale
	1ps
$end
$scope module JK_FF_tb $end
$var wire 1 ! Q_bar $end
$var wire 1 " Q $end
$var reg 1 # J $end
$var reg 1 $ K $end
$var reg 1 % clk $end
$var reg 1 & reset $end
$scope module uut $end
$var wire 1 # J $end
$var wire 1 $ K $end
$var wire 1 ! Q_bar $end
$var wire 1 % clk $end
$var wire 1 & reset $end
$var reg 1 " Q $end
$upscope $end
$upscope $end
$enddefinitions $end
$comment Show the parameter values. $end
$dumpall
$end
#0
$dumpvars
0&
0%
0$
0#
x"
x!
$end
#5000
1%
#10000
1!
0"
0%
1&
#15000
1%
#20000
0%
0&
#25000
1%
#30000
0%
#35000
1%
#40000
0%
1$
#45000
1%
#50000
0%
0$
1#
#55000
0!
1"
1%
#60000
0%
1$
#65000
1!
0"
1%
#70000
0%
0#
#75000
1%
#80000
0%
0$
1#
#85000
0!
1"
1%
#90000
0%
1$
#95000
1!
0"
1%
#100000
0%
#105000
0!
1"
1%
#110000
0%
#115000
1!
0"
1%
#120000
0%
#125000
0!
1"
1%
#130000
0%
#135000
1!
0"
1%
