flipflop-t/flipflop-t.v
module T_FF (
    input wire T,     // Entrada T
    input wire clk,   // Reloj
    input wire reset, // Señal de reset asincrónico
    output reg Q      // Salida Q
);

    always @(posedge clk or posedge reset) begin
        if (reset) begin
            Q <= 1'b0; // Reset, establece Q a 0
        end else begin
            if (T) begin
                Q <= ~Q; // Invierte Q en el flanco de subida del reloj si T es 1
            end
        end
    end

endmodule

flipflop-t/flipflop-t_tb.v
`timescale 1ns / 1ps
`default_nettype none
`define DUMPSTR(x) `"x.vcd`"

module T_FF_tb;

    // Parámetros de tiempo
    parameter PERIOD = 10; // Periodo del reloj (en unidades de tiempo)
    
    // Declaración de señales
    reg T;          // Entrada T
    reg clk;        // Reloj
    reg reset;      // Señal de reset
    wire Q;         // Salida Q

    // Instancia del flip-flop T
    T_FF uut (
        .T(T),
        .clk(clk),
        .reset(reset),
        .Q(Q)
    );

    // Generación del reloj
    always #((PERIOD / 2)) clk = ~clk; // Genera un ciclo de reloj de 50% de duty cycle

    // Inicialización de señales
    initial begin
        $dumpfile(`DUMPSTR(`VCD_OUTPUT));
        $dumpvars(0, T_FF_tb);

        clk = 0;
        reset = 1; // Activa el reset inicialmente
        #100;     // Espera un poco de tiempo
        reset = 0; // Desactiva el reset
        #100;     // Espera un poco de tiempo

        // Prueba de diferentes valores de entrada T
        #10 T = 1; #10 T = 0; #10 T = 1; #10 T = 1; #10 T = 0; #10 T = 1; #10 T = 1; #10 T = 0;
        #100;     // Espera un poco de tiempo

        // Finaliza la simulación
        $finish;
    end

    // Monitorear cambios en las señales
    initial begin
        $monitor("Time=%0t, T=%b, clk=%b, reset=%b, Q=%b", $time, T, clk, reset, Q);
    end

endmodule

flipflop-t/flipflop-t_tb.vcd
$date
	Wed May 15 14:12:27 2024
$end
$version
	Icarus Verilog
$end
$timescale
	1ps
$end
$scope module T_FF_tb $end
$var wire 1 ! Q $end
$var parameter 32 " PERIOD $end
$var reg 1 # T $end
$var reg 1 $ clk $end
$var reg 1 % reset $end
$scope module uut $end
$var wire 1 # T $end
$var wire 1 $ clk $end
$var wire 1 % reset $end
$var reg 1 ! Q $end
$upscope $end
$upscope $end
$enddefinitions $end
$comment Show the parameter values. $end
$dumpall
b1010 "
$end
#0
$dumpvars
1%
0$
x#
0!
$end
#5000
1$
#10000
0$
#15000
1$
#20000
0$
#25000
1$
#30000
0$
#35000
1$
#40000
0$
#45000
1$
#50000
0$
#55000
1$
#60000
0$
#65000
1$
#70000
0$
#75000
1$
#80000
0$
#85000
1$
#90000
0$
#95000
1$
#100000
0$
0%
#105000
1$
#110000
0$
#115000
1$
#120000
0$
#125000
1$
#130000
0$
#135000
1$
#140000
0$
#145000
1$
#150000
0$
#155000
1$
#160000
0$
#165000
1$
#170000
0$
#175000
1$
#180000
0$
#185000
1$
#190000
0$
#195000
1$
#200000
0$
#205000
1$
#210000
0$
1#
#215000
1!
1$
#220000
0$
0#
#225000
1$
#230000
0$
1#
#235000
0!
1$
#240000
0$
#245000
1!
1$
#250000
0$
0#
#255000
1$
#260000
0$
1#
#265000
0!
1$
#270000
0$
#275000
1!
1$
#280000
0$
0#
